neoloop/__init__.py
neoloop/assembly.py
neoloop/callers.py
neoloop/util.py
neoloop/cnv/__init__.py
neoloop/cnv/correctcnv.py
neoloop/cnv/loadcnv.py
neoloop/cnv/runcnv.py
neoloop/cnv/segcnv.py
neoloop/cnv/simcnv.py
neoloop/data/HMM-model.pkl
neoloop/data/gm.insitu.expected.10k.pkl
neoloop/data/gm.insitu.expected.20k.pkl
neoloop/data/gm.insitu.expected.25k.pkl
neoloop/data/gm.insitu.expected.40k.pkl
neoloop/data/gm.insitu.expected.50k.pkl
neoloop/data/gm.insitu.expected.5k.pkl
neoloop/data/peakachu-model-links.pkl
neoloop/pastis/__init__.py
neoloop/pastis/pastis.py
neoloop/pastis/possion_model.py
neoloop/tadtool/__init__.py
neoloop/tadtool/core.py
neoloop/tadtool/hmm.py
neoloop/visualize/__init__.py
neoloop/visualize/base.py
neoloop/visualize/bed.py
neoloop/visualize/bigwig.py
neoloop/visualize/core.py
neoloop/visualize/loops.py
neoloop-0.4.3.post2.data/scripts/add_prefix_to_cool.py
neoloop-0.4.3.post2.data/scripts/assemble-complexSVs
neoloop-0.4.3.post2.data/scripts/calculate-cnv
neoloop-0.4.3.post2.data/scripts/correct-cnv
neoloop-0.4.3.post2.data/scripts/neoloop-caller
neoloop-0.4.3.post2.data/scripts/neotad-caller
neoloop-0.4.3.post2.data/scripts/plot-cnv
neoloop-0.4.3.post2.data/scripts/prepare-SV-breakpoints.py
neoloop-0.4.3.post2.data/scripts/searchSVbyGene
neoloop-0.4.3.post2.data/scripts/segment-cnv
neoloop-0.4.3.post2.data/scripts/simulate-cnv
neoloop-0.4.3.post2.dist-info/LICENSE
neoloop-0.4.3.post2.dist-info/METADATA
neoloop-0.4.3.post2.dist-info/WHEEL
neoloop-0.4.3.post2.dist-info/top_level.txt
neoloop-0.4.3.post2.dist-info/RECORD
