Metadata-Version: 2.1
Name: neoloop
Version: 0.4.3.post2
Summary: Predict neo-loops induced by structural variations
Home-page: https://github.com/XiaoTaoWang/NeoLoopFinder
Author: XiaoTao Wang
Author-email: wangxiaotao686@gmail.com
Keywords: Hi-C cooler cancer enhancer hijacking
Classifier: Programming Language :: Python :: 3 :: Only
Classifier: Operating System :: POSIX
Classifier: Development Status :: 4 - Beta
Classifier: Intended Audience :: Science/Research
Classifier: Topic :: Scientific/Engineering :: Bio-Informatics
License-File: LICENSE
